components/Computer.py
components/Display.py
components/__init__.py
components/computer_system.py
components/processor.py
computer_sim/__init__.py
computer_sim-0.1.0.dist-info/METADATA
computer_sim-0.1.0.dist-info/WHEEL
computer_sim-0.1.0.dist-info/entry_points.txt
computer_sim-0.1.0.dist-info/top_level.txt
computer_sim-0.1.0.dist-info/RECORD
